whatsapp_export_md/__init__.py
whatsapp_export_md/cli.py
whatsapp_export_md-0.1.7.dist-info/licenses/LICENSE
whatsapp_export_md-0.1.7.dist-info/METADATA
whatsapp_export_md-0.1.7.dist-info/WHEEL
whatsapp_export_md-0.1.7.dist-info/entry_points.txt
whatsapp_export_md-0.1.7.dist-info/top_level.txt
whatsapp_export_md-0.1.7.dist-info/RECORD
