Metadata-Version: 2.4
Name: whatsapp-export-md
Version: 0.1.7
Summary: Convert WhatsApp exports to Markdown/HTML with media linking/embedding.
Author: Mohammed Shammas
License: MIT License
Project-URL: Homepage, https://github.com/mshammas/whatsapp-export-md
Project-URL: Issues, https://github.com/mshammas/whatsapp-export-md/issues
Keywords: whatsapp,markdown,html,export,chat,converter,embedding
Classifier: Programming Language :: Python :: 3
Classifier: License :: OSI Approved :: MIT License
Classifier: Operating System :: OS Independent
Classifier: Topic :: Text Processing :: Markup
Classifier: Topic :: Utilities
Requires-Python: >=3.9
License-File: LICENSE
Requires-Dist: python-dateutil>=2.9
Dynamic: license-file
